[
    {
      "id": 1,
      "name": "John Doe",
      "position": "CEO",
      "image": "https://via.placeholder.com/150"
    },
    {
      "id": 2,
      "name": "Jane Smith",
      "position": "CTO",
      "image": "https://via.placeholder.com/150"
    },
    {
      "id": 3,
      "name": "Alice Johnson",
      "position": "CFO",
      "image": "https://via.placeholder.com/150"
    },
    {
      "id": 4,
      "name": "Bob Brown",
      "position": "CMO",
      "image": "https://via.placeholder.com/150"
    },
    {
      "id": 5,
      "name": "Charlie Davis",
      "position": "COO",
      "image": "https://via.placeholder.com/150"
    },
    {
      "id": 6,
      "name": "Eva Green",
      "position": "CIO",
      "image": "https://via.placeholder.com/150"
    }
  ]